mne_qt_browser/__init__.py
mne_qt_browser/_colors.py
mne_qt_browser/_dialogs.py
mne_qt_browser/_fixes.py
mne_qt_browser/_graphic_items.py
mne_qt_browser/_pg_figure.py
mne_qt_browser/_utils.py
mne_qt_browser/_widgets.py
mne_qt_browser/figure.py
mne_qt_browser/docs/modify_epoch_click.md
mne_qt_browser/icons/README.rst
mne_qt_browser/icons/dark/index.theme
mne_qt_browser/icons/dark/actions/annotations.svg
mne_qt_browser/icons/dark/actions/crosshair.svg
mne_qt_browser/icons/dark/actions/fullscreen.svg
mne_qt_browser/icons/dark/actions/help.svg
mne_qt_browser/icons/dark/actions/less_channels.svg
mne_qt_browser/icons/dark/actions/less_time.svg
mne_qt_browser/icons/dark/actions/more_channels.svg
mne_qt_browser/icons/dark/actions/more_time.svg
mne_qt_browser/icons/dark/actions/overview_bar.svg
mne_qt_browser/icons/dark/actions/settings.svg
mne_qt_browser/icons/dark/actions/ssp.svg
mne_qt_browser/icons/dark/actions/zoom_in.svg
mne_qt_browser/icons/dark/actions/zoom_out.svg
mne_qt_browser/icons/light/index.theme
mne_qt_browser/icons/light/actions/annotations.svg
mne_qt_browser/icons/light/actions/crosshair.svg
mne_qt_browser/icons/light/actions/fullscreen.svg
mne_qt_browser/icons/light/actions/help.svg
mne_qt_browser/icons/light/actions/less_channels.svg
mne_qt_browser/icons/light/actions/less_time.svg
mne_qt_browser/icons/light/actions/more_channels.svg
mne_qt_browser/icons/light/actions/more_time.svg
mne_qt_browser/icons/light/actions/overview_bar.svg
mne_qt_browser/icons/light/actions/settings.svg
mne_qt_browser/icons/light/actions/ssp.svg
mne_qt_browser/icons/light/actions/zoom_in.svg
mne_qt_browser/icons/light/actions/zoom_out.svg
autocleaneeg_mne_qt_browser_fork-0.8.2.dist-info/METADATA
autocleaneeg_mne_qt_browser_fork-0.8.2.dist-info/WHEEL
autocleaneeg_mne_qt_browser_fork-0.8.2.dist-info/licenses/LICENSE
autocleaneeg_mne_qt_browser_fork-0.8.2.dist-info/RECORD
